README.txt
setup.cfg
setup.py
docs/HISTORY.txt
indra/__init__.py
indra.ipc.egg-info/PKG-INFO
indra.ipc.egg-info/SOURCES.txt
indra.ipc.egg-info/dependency_links.txt
indra.ipc.egg-info/entry_points.txt
indra.ipc.egg-info/namespace_packages.txt
indra.ipc.egg-info/not-zip-safe
indra.ipc.egg-info/paster_plugins.txt
indra.ipc.egg-info/requires.txt
indra.ipc.egg-info/top_level.txt
indra/ipc/__init__.py
indra/ipc/compatibility.py
indra/ipc/httputil.py
indra/ipc/llmessage.py
indra/ipc/llsdhttp.py
indra/ipc/mysql_pool.py
indra/ipc/russ.py
indra/ipc/saranwrap.py
indra/ipc/servicebuilder.py
indra/ipc/siesta.py
indra/ipc/siesta_test.py
indra/ipc/tokenstream.py
indra/ipc/webdav.py
indra/ipc/xml_rpc.py