Metadata-Version: 1.0
Name: indra.ipc
Version: 1.0
Summary: Indra support libs for IPC
Home-page: http://wiki.secondlife.com/wiki
Author: Linden Lab
Author-email: info@lindenlab.com
License: MIT License
Keywords: lindenlab secondlife indra virtualworlds
Platform: UNKNOWN
Classifier: Programming Language :: Python
Classifier: Topic :: Software Development :: Libraries :: Python Modules
